jsonshower/__init__.py
jsonshower/_version.py
jsonshower/docs.py
jsonshower/errors.py
jsonshower/pdfs.py
jsonshower/string_replace.py
jsonshower/viewer.py
jsonshower-2.2.12.dist-info/METADATA
jsonshower-2.2.12.dist-info/WHEEL
jsonshower-2.2.12.dist-info/top_level.txt
jsonshower-2.2.12.dist-info/RECORD
