Metadata-Version: 2.1
Name: jsonshower
Version: 2.2.12
Summary: Json Viewer with additional multimedia and highlighting support
Home-page: https://github.com/RelevanceAI/jsonviewer
Author: Jacky Wong
Author-email: jacky.wong@vctr.ai
License: UNKNOWN
Platform: UNKNOWN
Requires-Dist: pandas
Requires-Dist: fuzzysearch
Provides-Extra: pdfs
Requires-Dist: pdf-annotate ; extra == 'pdfs'
Requires-Dist: pdf2image ; extra == 'pdfs'
